{
  "type": "knowledgeWrite",
  "properties": {
    "text": "知识库写入",
    "remarks": "",
    "options": {
      "writeType": "text",
      "knowIds": [],
      "content": "",
      "fileSources": [],
      "segmentStrategy": "auto",
      "separator": "\\n",
      "customSeparator": "",
      "maxSegment": 800,
      "overlap": 10,
      "textRules": [],
      "waitForVectorize": false,
      "waitTimeout": 300,
      "vectorizeFailStrategy": "ignore"
    },
    "inputParams": [],
    "outputParams": [
      {
        "field": "documentId",
        "name": "documentId",
        "type": "string"
      },
      {
        "field": "documentIds",
        "name": "documentIds",
        "type": "string[]"
      }
    ]
  }
}